README.md
setup.py
lib/__init__.py
lib/lxml_to_dict.py
lib/lxml_to_dict.egg-info/PKG-INFO
lib/lxml_to_dict.egg-info/SOURCES.txt
lib/lxml_to_dict.egg-info/dependency_links.txt
lib/lxml_to_dict.egg-info/top_level.txt