Metadata-Version: 1.1
Name: lxml-to-dict
Version: 0.1.0
Summary: A simple conversion of an lxml.objectify element to a python dictionary.
Home-page: https://bitbucket.org/westmont/lxml_to_dict
Author: Connor Riva
Author-email: criva@westmont.edu
License: UNKNOWN
Platform: UNKNOWN
Classifier: Development Status :: 3 - Alpha
Classifier: Intended Audience :: Developers
Classifier: License :: OSI Approved :: MIT License
Classifier: Programming Language :: Python :: 2
Classifier: Programming Language :: Python :: 3
